README.md
igrep.py
setup.py
igrep.egg-info/PKG-INFO
igrep.egg-info/SOURCES.txt
igrep.egg-info/dependency_links.txt
igrep.egg-info/entry_points.txt
igrep.egg-info/requires.txt
igrep.egg-info/top_level.txt