Metadata-Version: 1.1
Name: igrep
Version: 0.9.5
Summary: Find image files by attributes like dimension and aspect ratio.
Home-page: UNKNOWN
Author: Jeremy Cantrell
Author-email: jmcantrell@gmail.com
License: UNKNOWN
Platform: UNKNOWN
Classifier: Development Status :: 4 - Beta
Classifier: Environment :: Console
Classifier: Intended Audience :: End Users/Desktop
Classifier: License :: Public Domain
Classifier: Natural Language :: English
Classifier: Operating System :: OS Independent
Classifier: Programming Language :: Python
